{"parameters":{"result":{"drawNo":"2024/139","drawDate":1734969600000,"drawDateStr":"2024-12-24","number1":8,"number2":11,"number3":18,"number4":23,"number5":25,"number6":41,"numberX":45,"numbers":[8,11,18,23,25,41,45],"prize1Amount":"$0","prize1Qty":"0","prize2Amount":"$476,080","prize2Qty":"7","prize3Amount":"$49,780","prize3Qty":"178.5","prize4Amount":"9,600","prize4Qty":"377.5","prize5Amount":"640","prize5Qty":"9,755.7","prize6Amount":"320","prize6Qty":"9,650.5","prize7Amount":"40","prize7Qty":"178,035.4","matched":[false,false,false,false,false,false,false],"nextInfo":{"drawNo":"2024/140","drawDate":1735315200000,"drawDateStr":"2024-12-28","jackpot":"$53,000,000","jackpotDescription":" "},"jackpot":null,"updateDate":null},"statusCode":"0"}}