{"parameters":{"result":{"drawNo":"2026/034","drawDate":1774627200000,"drawDateStr":"2026-03-28","number1":11,"number2":21,"number3":26,"number4":27,"number5":42,"number6":45,"numberX":19,"numbers":[11,21,26,27,42,45,19],"prize1Amount":"$0","prize1Qty":"0","prize2Amount":"$0","prize2Qty":"0","prize3Amount":"$96,100","prize3Qty":"42.5","prize4Amount":"9,600","prize4Qty":"125","prize5Amount":"640","prize5Qty":"2,720.8","prize6Amount":"320","prize6Qty":"3,973.7","prize7Amount":"40","prize7Qty":"53,558.5","matched":[false,false,false,false,false,false,false],"nextInfo":{"drawNo":"2026/035","drawDate":1774886400000,"drawDateStr":"2026-03-31","jackpot":"$15,000,000","jackpotDescription":" "},"jackpot":null,"updateDate":null},"statusCode":"0"}}